<annotation>
  <folder></folder>
  <filename>333.jpg</filename>
  <source>
    <database>Unknown</database>
    <annotation>Unknown</annotation>
    <image>Unknown</image>
  </source>
  <size>
    <width>410</width>
    <height>308</height>
    <depth></depth>
  </size>
  <segmented>0</segmented>
  <object>
    <name>me</name>
    <truncated>0</truncated>
    <occluded>0</occluded>
    <difficult>0</difficult>
    <bndbox>
      <xmin>172.98</xmin>
      <ymin>55.47</ymin>
      <xmax>208.39</xmax>
      <ymax>106.0</ymax>
    </bndbox>
    <attributes>
      <attribute>
        <name>rotation</name>
        <value>0.0</value>
      </attribute>
    </attributes>
  </object>
  <object>
    <name>black</name>
    <truncated>0</truncated>
    <occluded>0</occluded>
    <difficult>0</difficult>
    <bndbox>
      <xmin>29.81</xmin>
      <ymin>75.35</ymin>
      <xmax>149.9</xmax>
      <ymax>139.4</ymax>
    </bndbox>
    <attributes>
      <attribute>
        <name>rotation</name>
        <value>0.0</value>
      </attribute>
    </attributes>
  </object>
</annotation>
